{"parent":"minecraft:item/generated","textures":{"layer0":"minecraft:item/paper"},"overrides":[{"predicate":{"custom_model_data":0},"model":"minecraft:server_icons/2"},{"predicate":{"custom_model_data":1},"model":"minecraft:server_icons/446"},{"predicate":{"custom_model_data":2},"model":"minecraft:server_icons/412"},{"predicate":{"custom_model_data":3},"model":"minecraft:server_icons/1004"},{"predicate":{"custom_model_data":4},"model":"minecraft:server_icons/94"},{"predicate":{"custom_model_data":5},"model":"minecraft:server_icons/468"},{"predicate":{"custom_model_data":6},"model":"minecraft:server_icons/105"},{"predicate":{"custom_model_data":7},"model":"minecraft:server_icons/452"},{"predicate":{"custom_model_data":8},"model":"minecraft:server_icons/122"},{"predicate":{"custom_model_data":9},"model":"minecraft:server_icons/470"},{"predicate":{"custom_model_data":10},"model":"minecraft:server_icons/403"},{"predicate":{"custom_model_data":11},"model":"minecraft:server_icons/451"},{"predicate":{"custom_model_data":12},"model":"minecraft:server_icons/434"},{"predicate":{"custom_model_data":13},"model":"minecraft:server_icons/92"},{"predicate":{"custom_model_data":14},"model":"minecraft:server_icons/477"},{"predicate":{"custom_model_data":15},"model":"minecraft:server_icons/115"},{"predicate":{"custom_model_data":16},"model":"minecraft:server_icons/121"},{"predicate":{"custom_model_data":17},"model":"minecraft:server_icons/44"},{"predicate":{"custom_model_data":18},"model":"minecraft:server_icons/471"},{"predicate":{"custom_model_data":19},"model":"minecraft:server_icons/62"},{"predicate":{"custom_model_data":20},"model":"minecraft:server_icons/88"},{"predicate":{"custom_model_data":21},"model":"minecraft:server_icons/24"},{"predicate":{"custom_model_data":22},"model":"minecraft:server_icons/56"},{"predicate":{"custom_model_data":23},"model":"minecraft:server_icons/38"},{"predicate":{"custom_model_data":24},"model":"minecraft:server_icons/478"},{"predicate":{"custom_model_data":25},"model":"minecraft:server_icons/59"},{"predicate":{"custom_model_data":26},"model":"minecraft:server_icons/51"},{"predicate":{"custom_model_data":27},"model":"minecraft:server_icons/427"},{"predicate":{"custom_model_data":28},"model":"minecraft:server_icons/28"},{"predicate":{"custom_model_data":29},"model":"minecraft:server_icons/454"},{"predicate":{"custom_model_data":30},"model":"minecraft:server_icons/103"},{"predicate":{"custom_model_data":31},"model":"minecraft:server_icons/439"},{"predicate":{"custom_model_data":32},"model":"minecraft:server_icons/14"},{"predicate":{"custom_model_data":33},"model":"minecraft:server_icons/955"},{"predicate":{"custom_model_data":34},"model":"minecraft:server_icons/21"},{"predicate":{"custom_model_data":35},"model":"minecraft:server_icons/993"},{"predicate":{"custom_model_data":36},"model":"minecraft:server_icons/744"},{"predicate":{"custom_model_data":37},"model":"minecraft:server_icons/93"},{"predicate":{"custom_model_data":38},"model":"minecraft:server_icons/999"},{"predicate":{"custom_model_data":39},"model":"minecraft:server_icons/1000"},{"predicate":{"custom_model_data":40},"model":"minecraft:server_icons/411"},{"predicate":{"custom_model_data":41},"model":"minecraft:server_icons/73"},{"predicate":{"custom_model_data":42},"model":"minecraft:server_icons/1001"},{"predicate":{"custom_model_data":43},"model":"minecraft:server_icons/472"},{"predicate":{"custom_model_data":44},"model":"minecraft:server_icons/1002"},{"predicate":{"custom_model_data":45},"model":"minecraft:server_icons/1003"},{"predicate":{"custom_model_data":46},"model":"minecraft:server_icons/106"},{"predicate":{"custom_model_data":47},"model":"minecraft:server_icons/445"},{"predicate":{"custom_model_data":48},"model":"minecraft:server_icons/1018"},{"predicate":{"custom_model_data":49},"model":"minecraft:server_icons/426"},{"predicate":{"custom_model_data":50},"model":"minecraft:server_icons/444"},{"predicate":{"custom_model_data":51},"model":"minecraft:server_icons/1006"},{"predicate":{"custom_model_data":52},"model":"minecraft:server_icons/1007"},{"predicate":{"custom_model_data":53},"model":"minecraft:server_icons/1008"},{"predicate":{"custom_model_data":54},"model":"minecraft:server_icons/437"},{"predicate":{"custom_model_data":55},"model":"minecraft:server_icons/1009"},{"predicate":{"custom_model_data":56},"model":"minecraft:server_icons/1011"},{"predicate":{"custom_model_data":57},"model":"minecraft:server_icons/1013"},{"predicate":{"custom_model_data":58},"model":"minecraft:server_icons/4"},{"predicate":{"custom_model_data":59},"model":"minecraft:server_icons/997"},{"predicate":{"custom_model_data":60},"model":"minecraft:server_icons/72"},{"predicate":{"custom_model_data":61},"model":"minecraft:server_icons/58"},{"predicate":{"custom_model_data":62},"model":"minecraft:server_icons/470"},{"predicate":{"custom_model_data":63},"model":"minecraft:server_icons/51"},{"predicate":{"custom_model_data":64},"model":"minecraft:server_icons/412"},{"predicate":{"custom_model_data":65},"model":"minecraft:server_icons/21"},{"predicate":{"custom_model_data":66},"model":"minecraft:server_icons/1001"},{"predicate":{"custom_model_data":67},"model":"minecraft:server_icons/446"},{"predicate":{"custom_model_data":68},"model":"minecraft:server_icons/103"},{"predicate":{"custom_model_data":69},"model":"minecraft:server_icons/426"},{"predicate":{"custom_model_data":70},"model":"minecraft:server_icons/4"},{"predicate":{"custom_model_data":71},"model":"minecraft:server_icons/452"},{"predicate":{"custom_model_data":72},"model":"minecraft:server_icons/36"},{"predicate":{"custom_model_data":73},"model":"minecraft:server_icons/744"},{"predicate":{"custom_model_data":74},"model":"minecraft:server_icons/434"},{"predicate":{"custom_model_data":75},"model":"minecraft:server_icons/51"},{"predicate":{"custom_model_data":76},"model":"minecraft:server_icons/439"},{"predicate":{"custom_model_data":77},"model":"minecraft:server_icons/955"},{"predicate":{"custom_model_data":78},"model":"minecraft:server_icons/470"},{"predicate":{"custom_model_data":79},"model":"minecraft:server_icons/468"},{"predicate":{"custom_model_data":80},"model":"minecraft:server_icons/426"},{"predicate":{"custom_model_data":81},"model":"minecraft:server_icons/1007"},{"predicate":{"custom_model_data":82},"model":"minecraft:server_icons/2"},{"predicate":{"custom_model_data":83},"model":"minecraft:server_icons/38"},{"predicate":{"custom_model_data":84},"model":"minecraft:server_icons/1003"},{"predicate":{"custom_model_data":85},"model":"minecraft:server_icons/4"},{"predicate":{"custom_model_data":86},"model":"minecraft:server_icons/36"},{"predicate":{"custom_model_data":87},"model":"minecraft:server_icons/452"}]}